[
  {
    "title": "Fashionista",
    "description": "A list to auto install the Unoffical Patch and selection of the best Mods for this amazing game.",
    "author": "iunPause",
    "maintainers": [
      "github/daulvec"
    ],
    "game": "vtmb",
    "official": false,
    "tags": [
      "Steam",
      "GOG"
    ],
    "nsfw": false,
    "utility_list": false,
    "image_contains_title": true,
    "DisplayVersionOnlyInInstallerView": false,
    "force_down": false,
    "links": {
      "image": "https://raw.githubusercontent.com/daulvec/VtMB---Fashionista/main/img/Splash%20Design.webp",
      "readme": "https://github.com/daulvec/VtMB---Fashionista",
      "download": "https://authored-files.wabbajack.org/Fashionista-2.2.0.wabbajack_e7f66ebc-6107-4026-848a-b4ac9f4b9d22",
      "machineURL": "Fashionista",
      "discordURL": "https://discord.gg/iAmModlist",
      "websiteURL": "",
      "nexusCollection": {
        "collectionId": "424570",
        "slug": "d8yvch",
        "domainName": "vampirebloodlines",
        "lastRevisionNumber": 1
      }
    },
    "download_metadata": {
      "Hash": "lcxlAIsLWdM=",
      "Size": 49887683,
      "NumberOfArchives": 515,
      "SizeOfArchives": 52624278660,
      "NumberOfInstalledFiles": 414914,
      "SizeOfInstalledFiles": 70147766209,
      "TotalSize": 122772044869
    },
    "version": "2.2.0",
    "dateCreated": "1970-01-01T00:00:00Z",
    "dateUpdated": "2026-03-16T21:25:04.7846199Z",
    "repositoryName": ""
  },
  {
    "title": "Fashionista RTX Mod",
    "description": "Auto install the RTX Mod for VtMB.",
    "author": "iunPause",
    "maintainers": [
      "github/daulvec"
    ],
    "game": "vtmb",
    "official": false,
    "tags": [
      "Steam"
    ],
    "nsfw": false,
    "utility_list": false,
    "image_contains_title": true,
    "DisplayVersionOnlyInInstallerView": false,
    "force_down": false,
    "links": {
      "image": "https://raw.githubusercontent.com/daulvec/VtMB---Fashionista/main/img/RTX.webp",
      "readme": "https://iunpause.com/FashionistaRTX/Fashion-RTX.html",
      "download": "https://authored-files.wabbajack.org/Fashionista RTX Mod 0.1.2.wabbajack_9f2a0f52-7dcd-4b91-bdc7-4592c89d2d52",
      "machineURL": "FashionistaRTX",
      "discordURL": "https://discord.gg/iAmModlist",
      "websiteURL": "https://iunpause.com/",
      "nexusCollection": {
        "collectionId": "424723",
        "slug": "97vwcj",
        "domainName": "vampirebloodlines",
        "lastRevisionNumber": 1
      }
    },
    "download_metadata": {
      "Hash": "YhB4O1/7DuY=",
      "Size": 1762445,
      "NumberOfArchives": 5318,
      "SizeOfArchives": 13584725217,
      "NumberOfInstalledFiles": 27608,
      "SizeOfInstalledFiles": 18972210221,
      "TotalSize": 32556935438
    },
    "version": "0.1.2",
    "dateCreated": "1970-01-01T00:00:00Z",
    "dateUpdated": "2026-03-16T17:24:58.8664988Z",
    "repositoryName": ""
  }
]